django_adminlte/__init__.py
django_adminlte/admin.py
django_adminlte/apps.py
django_adminlte/compat.py
django_adminlte/defaults.py
django_adminlte/models.py
django_adminlte/tests.py
django_adminlte/urls.py
django_adminlte/views.py
django_adminlte/migrations/__init__.py
django_adminlte/static/README.md
django_adminlte/static/admin-lte/dist/css/AdminLTE.css
django_adminlte/static/admin-lte/dist/css/AdminLTE.min.css
django_adminlte/static/admin-lte/dist/css/skins/_all-skins.css
django_adminlte/static/admin-lte/dist/css/skins/_all-skins.min.css
django_adminlte/static/admin-lte/dist/css/skins/skin-black-light.css
django_adminlte/static/admin-lte/dist/css/skins/skin-black-light.min.css
django_adminlte/static/admin-lte/dist/css/skins/skin-black.css
django_adminlte/static/admin-lte/dist/css/skins/skin-black.min.css
django_adminlte/static/admin-lte/dist/css/skins/skin-blue-light.css
django_adminlte/static/admin-lte/dist/css/skins/skin-blue-light.min.css
django_adminlte/static/admin-lte/dist/css/skins/skin-blue.css
django_adminlte/static/admin-lte/dist/css/skins/skin-blue.min.css
django_adminlte/static/admin-lte/dist/css/skins/skin-green-light.css
django_adminlte/static/admin-lte/dist/css/skins/skin-green-light.min.css
django_adminlte/static/admin-lte/dist/css/skins/skin-green.css
django_adminlte/static/admin-lte/dist/css/skins/skin-green.min.css
django_adminlte/static/admin-lte/dist/css/skins/skin-purple-light.css
django_adminlte/static/admin-lte/dist/css/skins/skin-purple-light.min.css
django_adminlte/static/admin-lte/dist/css/skins/skin-purple.css
django_adminlte/static/admin-lte/dist/css/skins/skin-purple.min.css
django_adminlte/static/admin-lte/dist/css/skins/skin-red-light.css
django_adminlte/static/admin-lte/dist/css/skins/skin-red-light.min.css
django_adminlte/static/admin-lte/dist/css/skins/skin-red.css
django_adminlte/static/admin-lte/dist/css/skins/skin-red.min.css
django_adminlte/static/admin-lte/dist/css/skins/skin-yellow-light.css
django_adminlte2-0.4.3.dist-info/LICENSE.txt
django_adminlte2-0.4.3.dist-info/METADATA
django_adminlte2-0.4.3.dist-info/WHEEL
django_adminlte2-0.4.3.dist-info/top_level.txt
django_adminlte2-0.4.3.dist-info/RECORD
